beeradvocatereviews
