Metadata-Version: 1.1
Name: beeradvocatereviews
Version: 1.0.3
Summary: Module to export user reviews
Home-page: https://github.com/wontonst/beeradvocatereviews
Author: Roy Zheng
Author-email: UNKNOWN
License: MIT
Keywords: beeradvocate beer api
Platform: UNKNOWN
Classifier: License :: OSI Approved :: MIT License
